ja3requests/__init__.py
ja3requests/__version__.py
ja3requests/const.py
ja3requests/cookies.py
ja3requests/exceptions.py
ja3requests/response.py
ja3requests/sessions.py
ja3requests/utils.py
ja3requests/base/__contexts.py
ja3requests/base/__init__.py
ja3requests/base/__requests.py
ja3requests/base/__response.py
ja3requests/base/__sessions.py
ja3requests/base/__sockets.py
ja3requests/contexts/__init__.py
ja3requests/contexts/context.py
ja3requests/protocol/__init__.py
ja3requests/protocol/exceptions.py
ja3requests/protocol/sockets.py
ja3requests/requests/__init__.py
ja3requests/requests/http.py
ja3requests/requests/https.py
ja3requests/requests/request.py
ja3requests/sockets/__init__.py
ja3requests/sockets/http.py
ja3requests/sockets/https.py
ja3requests/sockets/proxy.py
ja3requests-1.1.0.dist-info/LICENSE
ja3requests-1.1.0.dist-info/METADATA
ja3requests-1.1.0.dist-info/WHEEL
ja3requests-1.1.0.dist-info/top_level.txt
ja3requests-1.1.0.dist-info/RECORD
