Metadata-Version: 2.1
Name: ja3requests
Version: 1.1.0
Summary: A http request library that can customize JA3 or H2 fingerprints.
Home-page: https://github.com/lxjmaster/ja3requests
Author: Mast Luo
Author-email: 379501669@qq.com
License: Apache-2.0 license
Keywords: pip,ja3requests,ja3,requests
Platform: any
License-File: LICENSE
